imio.annex-2.27.1-py3.13-nspkg.pth
imio/annex/__init__.py
imio/annex/adapters.py
imio/annex/behaviors.py
imio/annex/columns.py
imio/annex/configure.zcml
imio/annex/events.py
imio/annex/interfaces.py
imio/annex/overrides.zcml
imio/annex/patch.py
imio/annex/profiles.zcml
imio/annex/safe_utils.py
imio/annex/setuphandlers.py
imio/annex/utils.py
imio/annex/browser/__init__.py
imio/annex/browser/configure.zcml
imio/annex/browser/views.py
imio/annex/browser/static/view_element.png
imio/annex/content/__init__.py
imio/annex/content/annex.py
imio/annex/content/configure.zcml
imio/annex/content/events.py
imio/annex/locales/collective.eeafaceted.batchactions.pot
imio/annex/locales/collective.quickupload.pot
imio/annex/locales/imio.annex.pot
imio/annex/locales/plone.pot
imio/annex/locales/update.sh
imio/annex/locales/fr/LC_MESSAGES/collective.eeafaceted.batchactions.po
imio/annex/locales/fr/LC_MESSAGES/collective.quickupload.po
imio/annex/locales/fr/LC_MESSAGES/imio.annex.po
imio/annex/locales/fr/LC_MESSAGES/plone.po
imio/annex/profiles/default/browserlayer.xml
imio/annex/profiles/default/cssregistry.xml
imio/annex/profiles/default/imioannex_default.txt
imio/annex/profiles/default/jsregistry.xml
imio/annex/profiles/default/metadata.xml
imio/annex/profiles/default/propertiestool.xml
imio/annex/profiles/default/types.xml
imio/annex/profiles/default/workflows.xml
imio/annex/profiles/default/types/annex.xml
imio/annex/quickupload/__init__.py
imio/annex/quickupload/configure.zcml
imio/annex/quickupload/form.py
imio/annex/quickupload/quickupload.py
imio/annex/quickupload/utils.py
imio/annex/quickupload/static/helpers.js
imio/annex/quickupload/static/quickupload.css
imio/annex/quickupload/templates/form.pt
imio/annex/quickupload/templates/quick_upload.pt
imio_annex-2.27.1.dist-info/METADATA
imio_annex-2.27.1.dist-info/WHEEL
imio_annex-2.27.1.dist-info/entry_points.txt
imio_annex-2.27.1.dist-info/namespace_packages.txt
imio_annex-2.27.1.dist-info/top_level.txt
imio_annex-2.27.1.dist-info/RECORD
