Metadata-Version: 2.4
Name: imio.annex
Version: 2.27.1
Summary: An add-on for Plone
Home-page: https://pypi.python.org/pypi/imio.annex
Author: Martin Peeters
Author-email: martin.peeters@affinitic.be
License: GPL version 2
Keywords: Python Plone
Classifier: Development Status :: 6 - Mature
Classifier: Environment :: Web Environment
Classifier: Framework :: Plone
Classifier: Framework :: Plone :: 4.3
Classifier: Programming Language :: Python
Classifier: Programming Language :: Python :: 2.7
Classifier: Operating System :: OS Independent
Classifier: License :: OSI Approved :: GNU General Public License v2 (GPLv2)
Requires-Dist: collective.dms.scanbehavior>1.3.1
Requires-Dist: collective.documentviewer
Requires-Dist: collective.iconifiedcategory
Requires-Dist: collective.monkeypatcher
Requires-Dist: collective.quickupload
Requires-Dist: imio.dashboard
Requires-Dist: plone.api
Requires-Dist: plone.app.lockingbehavior
Requires-Dist: setuptools
Provides-Extra: test
Requires-Dist: plone.app.testing; extra == "test"
Requires-Dist: plone.app.contenttypes; extra == "test"
Requires-Dist: plone.app.robotframework[debug]; extra == "test"
Dynamic: author
Dynamic: author-email
Dynamic: classifier
Dynamic: description
Dynamic: home-page
Dynamic: keywords
Dynamic: license
Dynamic: provides-extra
Dynamic: requires-dist
Dynamic: summary
